Metadata-Version: 1.0
Name: iliadconn
Version: 0.1.2
Summary: get monthly outgoing traffic per iliad SIM
Home-page: UNKNOWN
Author: massimo
Author-email: massimo.cavalleri@gmail.com
License: GPL
Platform: UNKNOWN
